yabt/__init__.py
yabt/artifact.py
yabt/buildcontext.py
yabt/buildfile_parser.py
yabt/buildfile_parser_test.py
yabt/buildfile_utils.py
yabt/caching.py
yabt/caching_random_test.py
yabt/caching_test.py
yabt/cli.py
yabt/compat.py
yabt/config.py
yabt/docker.py
yabt/docker_test.py
yabt/dot.py
yabt/dot_test.py
yabt/extend.py
yabt/extend_test.py
yabt/fs_global_cache.py
yabt/glob.py
yabt/global_cache.py
yabt/graph.py
yabt/graph_test.py
yabt/gs_global_cache.py
yabt/logging.py
yabt/pkgmgmt.py
yabt/policy.py
yabt/policy_test.py
yabt/scm.py
yabt/target_extraction.py
yabt/target_extraction_test.py
yabt/target_info.py
yabt/target_info_test.py
yabt/target_utils.py
yabt/target_utils_test.py
yabt/test_utils.py
yabt/utils.py
yabt/utils_test.py
yabt/yabt.py
yabt/ybtbin.sh.tmpl
yabt/builders/__init__.py
yabt/builders/alias.py
yabt/builders/apt.py
yabt/builders/apt_test.py
yabt/builders/cpp.py
yabt/builders/cpp_caching_test.py
yabt/builders/cpp_test.py
yabt/builders/custom_installer.py
yabt/builders/custom_installer_test.py
yabt/builders/docker.py
yabt/builders/dockerapp.py
yabt/builders/extcommand.py
yabt/builders/filegroup.py
yabt/builders/filegroup_test.py
yabt/builders/fortests.py
yabt/builders/golang.py
yabt/builders/golang_test.py
yabt/builders/grunt.py
yabt/builders/nodejs.py
yabt/builders/proto.py
yabt/builders/proto_test.py
yabt/builders/python.py
yabt/builders/python_test.py
yabt/builders/ruby.py
yabt/builders/targetgroup.py
yabt/scm_providers/__init__.py
yabt/scm_providers/git.py
ybt-0.3.80.dist-info/LICENSE
ybt-0.3.80.dist-info/METADATA
ybt-0.3.80.dist-info/NOTICE
ybt-0.3.80.dist-info/WHEEL
ybt-0.3.80.dist-info/entry_points.txt
ybt-0.3.80.dist-info/top_level.txt
ybt-0.3.80.dist-info/zip-safe
ybt-0.3.80.dist-info/RECORD
