Metadata-Version: 2.1
Name: ybt
Version: 0.3.80
Summary: Yet another Build Tool
Home-page: https://github.com/resonai/ybt
Author: Itamar Ostricher
Author-email: yabt@resonai.com
License: Apache License, Version 2.0
Classifier: Programming Language :: Python
Classifier: Programming Language :: Python :: 3
Classifier: Programming Language :: Python :: 3.8
Classifier: Programming Language :: Python :: 3.9
Classifier: Programming Language :: Python :: 3.10
Classifier: Development Status :: 3 - Alpha
Classifier: Intended Audience :: Developers
Classifier: Environment :: Console
Classifier: License :: OSI Approved :: Apache Software License
Classifier: Operating System :: MacOS :: MacOS X
Classifier: Operating System :: POSIX :: Linux
Classifier: Topic :: Software Development :: Build Tools
License-File: LICENSE
License-File: NOTICE
Requires-Dist: argcomplete
Requires-Dist: colorama
Requires-Dist: ConfigArgParse
Requires-Dist: GitPython
Requires-Dist: munch
Requires-Dist: networkx >=2.0
Requires-Dist: ostrichlib
Requires-Dist: requests >=2.18.0
Requires-Dist: scandir
Requires-Dist: google-cloud-storage
Provides-Extra: test
Requires-Dist: pytest ; extra == 'test'
Requires-Dist: pytest-cov ; extra == 'test'
Requires-Dist: pytest-ruff ; extra == 'test'
